videosdk/plugins/gladia/__init__.py
videosdk/plugins/gladia/stt.py
videosdk/plugins/gladia/version.py
videosdk_plugins_gladia-0.0.58.dist-info/METADATA
videosdk_plugins_gladia-0.0.58.dist-info/WHEEL
videosdk_plugins_gladia-0.0.58.dist-info/RECORD
