Metadata-Version: 2.4
Name: videosdk-plugins-gladia
Version: 0.0.58
Summary: VideoSDK Agent Framework plugin for Gladia Speech-to-Text (STT)
Author: videosdk
License-Expression: Apache-2.0
Keywords: ai,audio,gladia,gladia.io,speech-to-text,stt,video,videosdk
Classifier: Development Status :: 4 - Beta
Classifier: Intended Audience :: Developers
Classifier: Topic :: Communications :: Conferencing
Classifier: Topic :: Multimedia :: Sound/Audio
Classifier: Topic :: Multimedia :: Video
Classifier: Topic :: Scientific/Engineering :: Artificial Intelligence
Requires-Python: >=3.12
Requires-Dist: aiohttp>=3.9.0
Requires-Dist: numpy>=1.26.0
Requires-Dist: scipy>=1.11.0
Requires-Dist: videosdk-agents>=0.0.58
